intento_queue/__init__.py
intento_queue/skeleton.py
intento_queue-0.0.1.dist-info/AUTHORS.rst
intento_queue-0.0.1.dist-info/LICENSE.txt
intento_queue-0.0.1.dist-info/METADATA
intento_queue-0.0.1.dist-info/WHEEL
intento_queue-0.0.1.dist-info/top_level.txt
intento_queue-0.0.1.dist-info/RECORD
