Metadata-Version: 2.1
Name: intento-queue
Version: 0.0.1
Summary: just a placeholder
Home-page: https://github.com/pyscaffold/pyscaffold/
Author: Alex
Author-email: me@sockeye.io
License: mit
Project-URL: Documentation, https://pyscaffold.org/
Platform: any
Classifier: Development Status :: 4 - Beta
Classifier: Programming Language :: Python
Provides-Extra: testing
Requires-Dist: pytest ; extra == 'testing'
Requires-Dist: pytest-cov ; extra == 'testing'
